{
  "ts": "2026-03-05T22:53:49.384508",
  "erasto": {
    "name": "Erasto",
    "end": 94188,
    "tr": 841.9,
    "cagr": 45.3,
    "mdd": -16.5,
    "mddq": "2026-Q1",
    "vol": 58.5,
    "dvol": 12.1,
    "wr": 58.3,
    "sharpe": 0.8,
    "sortino": 3.9,
    "calmar": 2.74,
    "ret_dd": 50.9,
    "best": "2020-Q4 (+107.4%)",
    "worst": "2026-Q1 (-16.5%)",
    "ag": 27.1,
    "al": -7.4,
    "pf": 3.67,
    "nq": 24,
    "wq": 14,
    "lq": 10
  },
  "btc": {
    "name": "BTC B&H",
    "end": 110993,
    "tr": 1009.9,
    "cagr": 49.4,
    "mdd": -71.9,
    "mddq": "2022-Q4",
    "vol": 96.2,
    "dvol": 33.4,
    "wr": 62.5,
    "sharpe": 0.76,
    "sortino": 2.18,
    "calmar": 0.69,
    "ret_dd": 14.0,
    "best": "2020-Q4 (+168.8%)",
    "worst": "2022-Q2 (-56.5%)",
    "ag": 43.0,
    "al": -20.6,
    "pf": 2.09,
    "nq": 24,
    "wq": 15,
    "lq": 9
  },
  "rolling": [
    {
      "q": "2022-Q1",
      "ret": 497.9,
      "mdd": -10.8,
      "vol": 82.0,
      "sh": 1.44
    },
    {
      "q": "2022-Q2",
      "ret": 333.6,
      "mdd": -12.8,
      "vol": 86.6,
      "sh": 1.17
    },
    {
      "q": "2022-Q3",
      "ret": 286.2,
      "mdd": -13.1,
      "vol": 88.0,
      "sh": 1.08
    },
    {
      "q": "2022-Q4",
      "ret": 80.7,
      "mdd": -15.7,
      "vol": 63.0,
      "sh": 0.64
    },
    {
      "q": "2023-Q1",
      "ret": 8.5,
      "mdd": -15.7,
      "vol": 21.2,
      "sh": 0.1
    },
    {
      "q": "2023-Q2",
      "ret": 25.3,
      "mdd": -15.7,
      "vol": 19.0,
      "sh": 0.48
    },
    {
      "q": "2023-Q3",
      "ret": -1.9,
      "mdd": -15.7,
      "vol": 14.2,
      "sh": -0.28
    },
    {
      "q": "2023-Q4",
      "ret": 16.2,
      "mdd": -15.7,
      "vol": 21.1,
      "sh": 0.27
    },
    {
      "q": "2024-Q1",
      "ret": 53.4,
      "mdd": -14.3,
      "vol": 27.4,
      "sh": 0.78
    },
    {
      "q": "2024-Q2",
      "ret": 61.8,
      "mdd": -6.5,
      "vol": 26.0,
      "sh": 0.91
    },
    {
      "q": "2024-Q3",
      "ret": 58.9,
      "mdd": -8.5,
      "vol": 26.3,
      "sh": 0.87
    },
    {
      "q": "2024-Q4",
      "ret": 112.5,
      "mdd": -8.5,
      "vol": 29.0,
      "sh": 1.35
    },
    {
      "q": "2025-Q1",
      "ret": 55.4,
      "mdd": -16.3,
      "vol": 33.8,
      "sh": 0.71
    },
    {
      "q": "2025-Q2",
      "ret": 63.8,
      "mdd": -16.3,
      "vol": 33.7,
      "sh": 0.79
    },
    {
      "q": "2025-Q3",
      "ret": 87.1,
      "mdd": -16.3,
      "vol": 32.3,
      "sh": 1.04
    },
    {
      "q": "2025-Q4",
      "ret": 59.7,
      "mdd": -16.3,
      "vol": 30.5,
      "sh": 0.8
    },
    {
      "q": "2026-Q1",
      "ret": 2.7,
      "mdd": -16.5,
      "vol": 28.5,
      "sh": 0.04
    }
  ]
}